protonvpn_cli/__init__.py
protonvpn_cli/__main__.py
protonvpn_cli/cli.py
protonvpn_cli/connection.py
protonvpn_cli/constants.py
protonvpn_cli/country_codes.py
protonvpn_cli/logger.py
protonvpn_cli/utils.py
protonvpn_cli/templates/openvpn_template.j2
protonvpn_cli-2.2.11.dist-info/AUTHORS
protonvpn_cli-2.2.11.dist-info/LICENSE
protonvpn_cli-2.2.11.dist-info/METADATA
protonvpn_cli-2.2.11.dist-info/WHEEL
protonvpn_cli-2.2.11.dist-info/entry_points.txt
protonvpn_cli-2.2.11.dist-info/top_level.txt
protonvpn_cli-2.2.11.dist-info/RECORD
