Metadata-Version: 2.1
Name: protonvpn-cli
Version: 2.2.11
Summary: Linux command-line client for ProtonVPN
Home-page: https://github.com/protonvpn/linux-cli-community
Author: Proton Technologies AG
Author-email: contact@protonvpn.com
License: GPLv3
Platform: UNKNOWN
Classifier: Development Status :: 4 - Beta
Classifier: Environment :: Console
Classifier: License :: OSI Approved :: GNU General Public License v3 (GPLv3)
Classifier: Programming Language :: Python
Classifier: Programming Language :: Python :: 3
Classifier: Programming Language :: Python :: 3.5
Classifier: Programming Language :: Python :: 3.6
Classifier: Programming Language :: Python :: 3.7
Classifier: Programming Language :: Python :: 3.8
Requires-Python: >=3.5
